rocher/__init__.py
rocher/flask.py
rocher/rocher.py
rocher/version.py
rocher/vs/LICENSE
rocher/vs/ThirdPartyNotices.txt
rocher/vs/loader.js
rocher/vs/nls.messages.de.js
rocher/vs/nls.messages.es.js
rocher/vs/nls.messages.fr.js
rocher/vs/nls.messages.it.js
rocher/vs/nls.messages.ja.js
rocher/vs/nls.messages.ko.js
rocher/vs/nls.messages.ru.js
rocher/vs/nls.messages.zh-cn.js
rocher/vs/nls.messages.zh-tw.js
rocher/vs/base/browser/ui/codicons/codicon/codicon.ttf
rocher/vs/base/worker/workerMain.js
rocher/vs/basic-languages/abap/abap.js
rocher/vs/basic-languages/apex/apex.js
rocher/vs/basic-languages/azcli/azcli.js
rocher/vs/basic-languages/bat/bat.js
rocher/vs/basic-languages/bicep/bicep.js
rocher/vs/basic-languages/cameligo/cameligo.js
rocher/vs/basic-languages/clojure/clojure.js
rocher/vs/basic-languages/coffee/coffee.js
rocher/vs/basic-languages/cpp/cpp.js
rocher/vs/basic-languages/csharp/csharp.js
rocher/vs/basic-languages/csp/csp.js
rocher/vs/basic-languages/css/css.js
rocher/vs/basic-languages/cypher/cypher.js
rocher/vs/basic-languages/dart/dart.js
rocher/vs/basic-languages/dockerfile/dockerfile.js
rocher/vs/basic-languages/ecl/ecl.js
rocher/vs/basic-languages/elixir/elixir.js
rocher/vs/basic-languages/flow9/flow9.js
rocher/vs/basic-languages/freemarker2/freemarker2.js
rocher/vs/basic-languages/fsharp/fsharp.js
rocher/vs/basic-languages/go/go.js
rocher/vs/basic-languages/graphql/graphql.js
rocher/vs/basic-languages/handlebars/handlebars.js
rocher/vs/basic-languages/hcl/hcl.js
rocher/vs/basic-languages/html/html.js
rocher/vs/basic-languages/ini/ini.js
rocher/vs/basic-languages/java/java.js
rocher/vs/basic-languages/javascript/javascript.js
rocher/vs/basic-languages/julia/julia.js
rocher/vs/basic-languages/kotlin/kotlin.js
rocher/vs/basic-languages/less/less.js
rocher/vs/basic-languages/lexon/lexon.js
rocher/vs/basic-languages/liquid/liquid.js
rocher/vs/basic-languages/lua/lua.js
rocher/vs/basic-languages/m3/m3.js
rocher/vs/basic-languages/markdown/markdown.js
rocher-0.52.2.dist-info/METADATA
rocher-0.52.2.dist-info/WHEEL
rocher-0.52.2.dist-info/licenses/LICENCE
rocher-0.52.2.dist-info/RECORD
