Metadata-Version: 2.4
Name: rocher
Version: 0.52.2
Summary: Rocher is wrapper arround the Monaco code Editor. It can be embed into any Python web application. Helper for Flask is provided.
Project-URL: Documentation, https://github.com/julien-duponchelle/rocher#readme
Project-URL: Issues, https://github.com/julien-duponchelle/rocher/issues
Project-URL: Source, https://github.com/julien-duponchelle/rocher
Author-email: Julien Duponchelle <julien@duponchelle.info>
License-Expression: MIT
License-File: LICENCE
Keywords: Monaco,code,diff,editor
Classifier: Development Status :: 4 - Beta
Classifier: Environment :: Web Environment
Classifier: Framework :: Flask
Classifier: License :: OSI Approved :: MIT License
Classifier: Programming Language :: Python
Classifier: Programming Language :: Python :: 3.7
Classifier: Programming Language :: Python :: 3.8
Classifier: Programming Language :: Python :: 3.9
Classifier: Programming Language :: Python :: 3.10
Classifier: Programming Language :: Python :: 3.11
Classifier: Programming Language :: Python :: Implementation :: CPython
Classifier: Programming Language :: Python :: Implementation :: PyPy
Requires-Python: >=3.7
